unsupervised_multimodal_trajectory_modeling/__init__.py
unsupervised_multimodal_trajectory_modeling/linear_gaussian/__init__.py
unsupervised_multimodal_trajectory_modeling/linear_gaussian/marginalizable_mixture_model.py
unsupervised_multimodal_trajectory_modeling/linear_gaussian/marginalizable_state_space_model.py
unsupervised_multimodal_trajectory_modeling/nonlinear/__init__.py
unsupervised_multimodal_trajectory_modeling/nonlinear/state_space_model.py
unsupervised_multimodal_trajectory_modeling/nonlinear/state_space_model_classifier.py
unsupervised_multimodal_trajectory_modeling/nonlinear/state_space_model_knn.py
unsupervised_multimodal_trajectory_modeling/nonlinear/state_space_model_linear_gaussian.py
unsupervised_multimodal_trajectory_modeling/nonlinear/state_space_model_linear_trans_knn_meas.py
unsupervised_multimodal_trajectory_modeling/nonlinear/state_space_model_mixture.py
unsupervised_multimodal_trajectory_modeling/util/__init__.py
unsupervised_multimodal_trajectory_modeling/util/util_post_hoc.py
unsupervised_multimodal_trajectory_modeling/util/util_state_space.py
unsupervised_multimodal_trajectory_modeling-2024.2.2.dist-info/LICENSE.txt
unsupervised_multimodal_trajectory_modeling-2024.2.2.dist-info/METADATA
unsupervised_multimodal_trajectory_modeling-2024.2.2.dist-info/WHEEL
unsupervised_multimodal_trajectory_modeling-2024.2.2.dist-info/top_level.txt
unsupervised_multimodal_trajectory_modeling-2024.2.2.dist-info/RECORD
