Metadata-Version: 2.1
Name: unsupervised-multimodal-trajectory-modeling
Version: 2024.2.2
Summary: trains mixtures of state space models with expectation maximization
Author-email: "Michael C. Burkhart" <mcb93@cam.ac.uk>
License: MIT License
Project-URL: Homepage, https://pypi.org/project/unsupervised-multimodal-trajectory-modeling/
Project-URL: Repository, https://github.com/burkh4rt/Unsupervised-Multimodal-Trajectory-Modeling
Keywords: unsupervised clustering,trajectory clustering,mixture models,state space models,machine learning
Classifier: Development Status :: 2 - Pre-Alpha
Classifier: Intended Audience :: Science/Research
Classifier: License :: OSI Approved :: MIT License
Classifier: Natural Language :: English
Classifier: Programming Language :: Python :: 3
Classifier: Topic :: Scientific/Engineering :: Artificial Intelligence
Requires-Python: >=3.10
License-File: LICENSE.txt
Requires-Dist: matplotlib >=3.8
Requires-Dist: numba >=0.59
Requires-Dist: numpy >=1.26
Requires-Dist: pandas >=2.2
Requires-Dist: pip >=24.0
Requires-Dist: scikit-learn >=1.4
Requires-Dist: scipy >=1.12
Requires-Dist: seaborn >=0.13
Requires-Dist: statsmodels >=0.14
Requires-Dist: tabulate >=0.9
